{
  "columns": [
    {
      "name": "Team",
      "datatype": "String",
      "bit_settings": "",
      "values": [
        "Jets\n            \n          \n\n            Jets",
        "Raiders\n            \n          \n\n            Raiders",
        "Bills\n            \n          \n\n            Bills",
        "Lions\n            \n          \n\n            Lions",
        "Chargers\n            \n          \n\n            Chargers",
        "Giants\n            \n          \n\n            Giants",
        "Rams\n            \n          \n\n            Rams",
        "Bengals\n            \n          \n\n            Bengals",
        "Cowboys\n            \n          \n\n            Cowboys",
        "Eagles\n            \n          \n\n            Eagles",
        "Steelers\n            \n          \n\n            Steelers",
        "Dolphins\n            \n          \n\n            Dolphins",
        "Broncos\n            \n          \n\n            Broncos",
        "Packers\n            \n          \n\n            Packers",
        "49ers\n            \n          \n\n            49ers",
        "Seahawks\n            \n          \n\n            Seahawks",
        "Oilers\n            \n          \n\n            Oilers",
        "Vikings\n            \n          \n\n            Vikings",
        "Cardinals\n            \n          \n\n            Cardinals",
        "Redskins\n            \n          \n\n            Redskins",
        "Bears\n            \n          \n\n            Bears",
        "Falcons\n            \n          \n\n            Falcons",
        "Browns\n            \n          \n\n            Browns",
        "Chiefs\n            \n          \n\n            Chiefs",
        "Saints\n            \n          \n\n            Saints",
        "Buccaneers\n            \n          \n\n            Buccaneers",
        "Patriots\n            \n          \n\n            Patriots",
        "Colts\n            \n          \n\n            Colts"
      ]
    },
    {
      "name": "Sck",
      "datatype": "String",
      "bit_settings": "",
      "values": [
        "30",
        "53",
        "16",
        "44",
        "19",
        "47",
        "50",
        "35",
        "31",
        "22",
        "27",
        "30",
        "61",
        "52",
        "29",
        "37",
        "40",
        "29",
        "48",
        "30",
        "35",
        "37",
        "40",
        "37",
        "41",
        "19",
        "45",
        "37"
      ]
    },
    {
      "name": "Comb",
      "datatype": "String",
      "bit_settings": "",
      "values": [
        "1063",
        "858",
        "852",
        "869",
        "898",
        "800",
        "877",
        "872",
        "965",
        "838",
        "844",
        "894",
        "858",
        "815",
        "1038",
        "886",
        "864",
        "845",
        "835",
        "926",
        "900",
        "880",
        "1024",
        "960",
        "916",
        "699",
        "820",
        "778"
      ]
    },
    {
      "name": "Asst",
      "datatype": "String",
      "bit_settings": "",
      "values": [
        "226",
        "88",
        "108",
        "54",
        "105",
        "62",
        "83",
        "74",
        "118",
        "56",
        "79",
        "103",
        "42",
        "43",
        "166",
        "155",
        "152",
        "91",
        "62",
        "104",
        "69",
        "98",
        "212",
        "145",
        "126",
        "22",
        "67",
        "75"
      ]
    },
    {
      "name": "Solo",
      "datatype": "String",
      "bit_settings": "",
      "values": [
        "749",
        "835",
        "762",
        "908",
        "821",
        "830",
        "856",
        "832",
        "880",
        "866",
        "832",
        "819",
        "917",
        "886",
        "835",
        "707",
        "704",
        "796",
        "864",
        "852",
        "911",
        "828",
        "748",
        "814",
        "801",
        "774",
        "820",
        "750"
      ]
    }
  ]
}