{
  "columns": [
    {
      "name": "Team",
      "datatype": "String",
      "bit_settings": "",
      "values": [
        "Bears\n            \n          \n\n            Bears",
        "Eagles\n            \n          \n\n            Eagles",
        "Giants\n            \n          \n\n            Giants",
        "Cardinals\n            \n          \n\n            Cardinals",
        "Jets\n            \n          \n\n            Jets",
        "Chargers\n            \n          \n\n            Chargers",
        "Chiefs\n            \n          \n\n            Chiefs",
        "Cowboys\n            \n          \n\n            Cowboys",
        "Ravens\n            \n          \n\n            Ravens",
        "Redskins\n            \n          \n\n            Redskins",
        "Steelers\n            \n          \n\n            Steelers",
        "Panthers\n            \n          \n\n            Panthers",
        "Oilers\n            \n          \n\n            Oilers",
        "Broncos\n            \n          \n\n            Broncos",
        "Patriots\n            \n          \n\n            Patriots",
        "Dolphins\n            \n          \n\n            Dolphins",
        "Vikings\n            \n          \n\n            Vikings",
        "Bengals\n            \n          \n\n            Bengals",
        "Seahawks\n            \n          \n\n            Seahawks",
        "Jaguars\n            \n          \n\n            Jaguars",
        "Lions\n            \n          \n\n            Lions",
        "Rams\n            \n          \n\n            Rams",
        "49ers\n            \n          \n\n            49ers",
        "Bills\n            \n          \n\n            Bills",
        "Packers\n            \n          \n\n            Packers",
        "Colts\n            \n          \n\n            Colts",
        "Buccaneers\n            \n          \n\n            Buccaneers",
        "Raiders\n            \n          \n\n            Raiders",
        "Falcons\n            \n          \n\n            Falcons",
        "Saints\n            \n          \n\n            Saints"
      ]
    },
    {
      "name": "3rd Att",
      "datatype": "String",
      "bit_settings": "",
      "values": [
        "3317",
        "3209",
        "3201",
        "3187",
        "3181",
        "3106",
        "3081",
        "3062",
        "3025",
        "3016",
        "3010",
        "2976",
        "2950",
        "2947",
        "2940",
        "2929",
        "2897",
        "2870",
        "2866",
        "2863",
        "2848",
        "2836",
        "2836",
        "2819",
        "2763",
        "2755",
        "2724",
        "2679",
        "2660",
        "2649"
      ]
    },
    {
      "name": "3rd Md",
      "datatype": "String",
      "bit_settings": "",
      "values": [
        "1198",
        "1199",
        "1008",
        "1115",
        "1213",
        "1023",
        "1278",
        "1113",
        "1091",
        "1277",
        "1351",
        "1312",
        "1247",
        "1246",
        "1186",
        "1112",
        "1155",
        "1179",
        "1165",
        "1125",
        "1002",
        "931",
        "1038",
        "706",
        "1099",
        "1042",
        "1056",
        "859",
        "942",
        "696"
      ]
    },
    {
      "name": "4th Att",
      "datatype": "String",
      "bit_settings": "",
      "values": [
        "353",
        "290",
        "120",
        "291",
        "280",
        "273",
        "215",
        "172",
        "277",
        "172",
        "249",
        "119",
        "186",
        "219",
        "174",
        "301",
        "143",
        "265",
        "198",
        "163",
        "232",
        "139",
        "106",
        "381",
        "67",
        "253",
        "190",
        "235",
        "163",
        "277"
      ]
    },
    {
      "name": "4th Md",
      "datatype": "String",
      "bit_settings": "",
      "values": [
        "185",
        "183",
        "67",
        "149",
        "161",
        "105",
        "67",
        "80",
        "160",
        "66",
        "152",
        "39",
        "120",
        "96",
        "41",
        "171",
        "65",
        "134",
        "101",
        "69",
        "101",
        "50",
        "52",
        "145",
        "67",
        "126",
        "68",
        "66",
        "101",
        "178"
      ]
    },
    {
      "name": "Rec 1st",
      "datatype": "String",
      "bit_settings": "",
      "values": [
        "188",
        "203",
        "124",
        "186",
        "173",
        "161",
        "163",
        "170",
        "176",
        "192",
        "157",
        "170",
        "136",
        "172",
        "173",
        "199",
        "177",
        "171",
        "207",
        "187",
        "166",
        "161",
        "167",
        "144",
        "191",
        "171",
        "134",
        "170",
        "168",
        "127"
      ]
    },
    {
      "name": "Rec 1st%",
      "datatype": "String",
      "bit_settings": "",
      "values": [
        "56",
        "61.5",
        "49.8",
        "58.7",
        "54.2",
        "55.3",
        "58",
        "54.1",
        "52.1",
        "67.8",
        "62.1",
        "58.8",
        "61.8",
        "59.9",
        "53.9",
        "59.9",
        "55.5",
        "56.6",
        "57.7",
        "59.7",
        "54.6",
        "59.4",
        "60.1",
        "49.2",
        "61.8",
        "53.9",
        "59.8",
        "57.8",
        "61.5",
        "55.7"
      ]
    },
    {
      "name": "Rush 1st",
      "datatype": "String",
      "bit_settings": "",
      "values": [
        "94",
        "105",
        "113",
        "79",
        "97",
        "70",
        "129",
        "82",
        "99",
        "86",
        "154",
        "91",
        "130",
        "138",
        "71",
        "87",
        "96",
        "104",
        "98",
        "103",
        "120",
        "85",
        "106",
        "98",
        "103",
        "109",
        "88",
        "74",
        "88",
        "78"
      ]
    },
    {
      "name": "Rush 1st%",
      "datatype": "String",
      "bit_settings": "",
      "values": [
        "19.2",
        "22.6",
        "21.7",
        "20",
        "22.5",
        "17.1",
        "24.4",
        "19.4",
        "23.6",
        "18.9",
        "26.9",
        "20.6",
        "24",
        "26.5",
        "17.8",
        "20.2",
        "21.4",
        "23",
        "24.3",
        "22.7",
        "26.8",
        "19.2",
        "20.3",
        "23.2",
        "22.4",
        "24.2",
        "18.4",
        "20.6",
        "19.9",
        "18.7"
      ]
    },
    {
      "name": "Scrm Plys",
      "datatype": "String",
      "bit_settings": "",
      "values": [
        "1128",
        "1116",
        "1027",
        "1075",
        "1043",
        "1025",
        "1054",
        "1015",
        "1043",
        "1034",
        "1058",
        "1019",
        "993",
        "1068",
        "960",
        "1032",
        "1022",
        "1002",
        "1049",
        "998",
        "1028",
        "1013",
        "999",
        "1014",
        "1004",
        "1035",
        "915",
        "947",
        "980",
        "925"
      ]
    }
  ]
}