{
  "columns": [
    {
      "name": "Team",
      "datatype": "String",
      "bit_settings": "",
      "values": [
        "Eagles\n            \n          \n\n            Eagles",
        "Bengals\n            \n          \n\n            Bengals",
        "Browns\n            \n          \n\n            Browns",
        "Buccaneers\n            \n          \n\n            Buccaneers",
        "Patriots\n            \n          \n\n            Patriots",
        "Cowboys\n            \n          \n\n            Cowboys",
        "Giants\n            \n          \n\n            Giants",
        "Rams\n            \n          \n\n            Rams",
        "Falcons\n            \n          \n\n            Falcons",
        "Texans\n            \n          \n\n            Texans",
        "Broncos\n            \n          \n\n            Broncos",
        "Vikings\n            \n          \n\n            Vikings",
        "Jets\n            \n          \n\n            Jets",
        "Jaguars\n            \n          \n\n            Jaguars",
        "Bears\n            \n          \n\n            Bears",
        "Lions\n            \n          \n\n            Lions",
        "Panthers\n            \n          \n\n            Panthers",
        "Steelers\n            \n          \n\n            Steelers",
        "Seahawks\n            \n          \n\n            Seahawks",
        "Ravens\n            \n          \n\n            Ravens",
        "Dolphins\n            \n          \n\n            Dolphins",
        "Chargers\n            \n          \n\n            Chargers",
        "Packers\n            \n          \n\n            Packers",
        "Cardinals\n            \n          \n\n            Cardinals",
        "Titans\n            \n          \n\n            Titans",
        "Bills\n            \n          \n\n            Bills",
        "Chiefs\n            \n          \n\n            Chiefs",
        "Colts\n            \n          \n\n            Colts",
        "Raiders\n            \n          \n\n            Raiders",
        "Redskins\n            \n          \n\n            Redskins",
        "Saints\n            \n          \n\n            Saints",
        "Niners\n            \n          \n\n            Niners"
      ]
    },
    {
      "name": "Avg",
      "datatype": "String",
      "bit_settings": "",
      "values": [
        "13.5",
        "11.8",
        "11.7",
        "11.6",
        "11.4",
        "10.9",
        "10.9",
        "10.7",
        "10",
        "10",
        "9.5",
        "9.5",
        "9.1",
        "8.6",
        "8.5",
        "8.3",
        "8.3",
        "8.1",
        "7.5",
        "7.4",
        "7.2",
        "7",
        "6.9",
        "6.8",
        "6.7",
        "6.6",
        "6.5",
        "5.2",
        "4.9",
        "4.8",
        "4.6",
        "4.4"
      ]
    },
    {
      "name": "Ret",
      "datatype": "String",
      "bit_settings": "",
      "values": [
        "35",
        "40",
        "39",
        "40",
        "38",
        "39",
        "36",
        "37",
        "27",
        "45",
        "44",
        "48",
        "50",
        "27",
        "39",
        "28",
        "34",
        "36",
        "46",
        "39",
        "33",
        "26",
        "34",
        "45",
        "33",
        "33",
        "32",
        "29",
        "36",
        "32",
        "33",
        "49"
      ]
    },
    {
      "name": "Yds",
      "datatype": "String",
      "bit_settings": "",
      "values": [
        "471",
        "474",
        "456",
        "462",
        "432",
        "426",
        "393",
        "395",
        "270",
        "449",
        "419",
        "455",
        "457",
        "233",
        "330",
        "233",
        "282",
        "290",
        "346",
        "290",
        "237",
        "183",
        "236",
        "308",
        "220",
        "218",
        "209",
        "151",
        "177",
        "152",
        "152",
        "216"
      ]
    },
    {
      "name": "PRet T",
      "datatype": "String",
      "bit_settings": "",
      "values": [
        "2",
        "0",
        "1",
        "1",
        "0",
        "2",
        "1",
        "0",
        "0",
        "0",
        "1",
        "0",
        "0",
        "0",
        "1",
        "0",
        "0",
        "0",
        "0",
        "0",
        "0",
        "1",
        "0",
        "0",
        "0",
        "0",
        "0",
        "0",
        "0",
        "0",
        "0",
        "0"
      ]
    },
    {
      "name": "20+",
      "datatype": "String",
      "bit_settings": "",
      "values": [
        "8",
        "4",
        "5",
        "4",
        "4",
        "6",
        "4",
        "6",
        "3",
        "7",
        "4",
        "5",
        "3",
        "3",
        "6",
        "1",
        "4",
        "3",
        "4",
        "3",
        "1",
        "1",
        "2",
        "4",
        "0",
        "4",
        "0",
        "1",
        "0",
        "1",
        "2",
        "0"
      ]
    },
    {
      "name": "40+",
      "datatype": "String",
      "bit_settings": "",
      "values": [
        "3",
        "2",
        "3",
        "1",
        "2",
        "2",
        "1",
        "1",
        "0",
        "2",
        "1",
        "0",
        "0",
        "2",
        "1",
        "1",
        "0",
        "0",
        "0",
        "0",
        "0",
        "1",
        "1",
        "1",
        "0",
        "0",
        "0",
        "0",
        "0",
        "1",
        "0",
        "0"
      ]
    },
    {
      "name": "Lng",
      "datatype": "String",
      "bit_settings": "",
      "values": [
        "85T",
        "60",
        "67T",
        "77T",
        "69",
        "82",
        "79",
        "56",
        "28",
        "62",
        "71",
        "36",
        "37",
        "44T",
        "49",
        "43",
        "37T",
        "25",
        "29",
        "34",
        "22",
        "77T",
        "45T",
        "64T",
        "18",
        "31T",
        "19",
        "22",
        "19",
        "43",
        "23T",
        "18"
      ]
    },
    {
      "name": "FC",
      "datatype": "String",
      "bit_settings": "",
      "values": [
        "19",
        "19",
        "3",
        "10",
        "19",
        "23",
        "18",
        "14",
        "14",
        "15",
        "16",
        "17",
        "26",
        "7",
        "7",
        "15",
        "11",
        "25",
        "12",
        "18",
        "13",
        "13",
        "12",
        "13",
        "22",
        "18",
        "24",
        "23",
        "23",
        "22",
        "17",
        "13"
      ]
    },
    {
      "name": "FUM",
      "datatype": "String",
      "bit_settings": "",
      "values": [
        "1",
        "2",
        "2",
        "1",
        "2",
        "5",
        "2",
        "5",
        "1",
        "2",
        "1",
        "3",
        "2",
        "3",
        "3",
        "3",
        "4",
        "2",
        "2",
        "3",
        "4",
        "3",
        "2",
        "4",
        "5",
        "7",
        "5",
        "2",
        "6",
        "6",
        "2",
        "8"
      ]
    },
    {
      "name": "P Blk",
      "datatype": "String",
      "bit_settings": "",
      "values": [
        "0",
        "0",
        "0",
        "2",
        "0",
        "0",
        "0",
        "0",
        "1",
        "0",
        "0",
        "0",
        "1",
        "0",
        "0",
        "0",
        "0",
        "0",
        "0",
        "0",
        "0",
        "1",
        "0",
        "0",
        "0",
        "0",
        "1",
        "0",
        "0",
        "0",
        "0",
        "0"
      ]
    }
  ]
}